<odoo>
    <record id="account_autocreate_partner_account_server_action" model="ir.actions.server">
        <field name="name">Erstelle Debitor- und Kreditorkonten</field>
        <field name="model_id" ref="base.model_res_partner"/>
        <field name="binding_model_id" ref="base.model_res_partner"/>
        <field name="binding_type">both</field>
        <field name="state">code</field>
        <field name="code"><![CDATA[
record.create_debtor_and_creditor_accounts()
        ]]></field>
    </record>
</odoo>
